pocket_to_bookmarks_html/__init__.py
pocket_to_bookmarks_html-0.2.1.dist-info/LICENSE
pocket_to_bookmarks_html-0.2.1.dist-info/METADATA
pocket_to_bookmarks_html-0.2.1.dist-info/WHEEL
pocket_to_bookmarks_html-0.2.1.dist-info/entry_points.txt
pocket_to_bookmarks_html-0.2.1.dist-info/top_level.txt
pocket_to_bookmarks_html-0.2.1.dist-info/RECORD
