Metadata-Version: 2.1
Name: pocket-to-bookmarks-html
Version: 0.2.1
Summary: A pocket to bookmarks.html converter
Author: David Poblador i Garcia
Project-URL: Homepage, https://github.com/davidpoblador/pocket-to-bookmarks-html
Project-URL: Issues, https://github.com/davidpoblador/pocket-to-bookmarks-html/issues
Classifier: Development Status :: 3 - Alpha
Classifier: Environment :: Console
Classifier: Intended Audience :: End Users/Desktop
Classifier: Operating System :: OS Independent
Classifier: Programming Language :: Python :: 3
Classifier: License :: OSI Approved :: MIT License
Requires-Python: >=3.9
License-File: LICENSE
Requires-Dist: beautifulsoup4 >=4.12.3
